{
    "TransportData": [
    ],
    "NpcsTimers": [
    ],
    "FactionData": [
        {
            "Points": 2000,
            "Faction": 0
        },
        {
            "Points": 0,
            "Faction": 2
        }
    ],
    "BankData": [
    ],
    "ItemGiversList": [
        {
            "Long": 1749766733126L,
            "Slot": 1
        }
    ],
    "QuestData": {
        "CompletedQuests": [
        ],
        "ActiveQuests": [
        ]
    },
    "PlayerCompanionId": 0,
    "DialogData": [
        {
            "Dialog": 1
        },
        {
            "Dialog": 2
        },
        {
            "Dialog": 3
        },
        {
            "Dialog": 5
        }
    ],
    "ItemGiverChained": [
    ],
    "MailData": [
    ],
    "PlayerName": "Se4norComediante",
    "UUID": "3fff8650-d897-3866-9c95-e06e18153e8f",
    "ScriptStoreddata": {
    }
}
